safeiofile/__init__.py
safeiofile-0.1.1.dist-info/licenses/LICENSE
safeiofile-0.1.1.dist-info/METADATA
safeiofile-0.1.1.dist-info/WHEEL
safeiofile-0.1.1.dist-info/top_level.txt
safeiofile-0.1.1.dist-info/RECORD
