Metadata-Version: 2.4
Name: safeiofile
Version: 0.1.1
Summary: Safely perform file I/O operations in Python — with backups and auto-rotation
Author-email: "Omkar D. Dorugade" <omkardorugade007@email.com>
License: MIT
Project-URL: Homepage, https://github.com/omkar086/safeiofile_Lib
Requires-Python: >=3.7
License-File: LICENSE
Dynamic: license-file
